
{
  "uuid": "i4fa82xvafvw",
  "slug": "salade-de-betterave-ya_i4fa82xvafvw",
  "title": "Salade De Betterave, Yaourt, Graines De Moutarde Et Ciboulette",
  "draft": false,
  "typeR": "entree",
  "categories": ["Salade"],
  "regime": ["sans-gluten","vegetarien"],
  "cuisson": false,
  "serveHot": false,
  "plate": 100,
  "quantite_desc": "env. 125 gr par personne",
  "check": true,
  "checkAlwaysOk": false,
  "materiel": null,
  "ingredients": [{
      "uuid": "mt22ff",
      "name": "Ciboulette",
      "originalQuantity": 5,
      "originalUnit": "bottes",
      "normalizedQuantity": 5,
      "normalizedUnit": "bottes",
      "comment": "",
      "allergens": [],
      "type": "epices"
    },{
      "uuid": "15qnl9",
      "name": "Moutarde à l'ancienne",
      "originalQuantity": 270,
      "originalUnit": "gr.",
      "normalizedQuantity": 270,
      "normalizedUnit": "gr.",
      "comment": "",
      "allergens": [],
      "type": "epices"
    },{
      "uuid": "hlbwfd",
      "name": "Yaourt de soja",
      "originalQuantity": 400,
      "originalUnit": "gr.",
      "normalizedQuantity": 400,
      "normalizedUnit": "gr.",
      "comment": "version végane (10/15pers)",
      "allergens": ["Soja"],
      "type": "frais"
    },{
      "uuid": "dzqmba",
      "name": "Yaourt grec de vache",
      "originalQuantity": 3.6,
      "originalUnit": "kg",
      "normalizedQuantity": 3600,
      "normalizedUnit": "gr.",
      "comment": "",
      "allergens": ["Produit laitier"],
      "type": "frais"
    },{
      "uuid": "i7psri",
      "name": "Betterave cuite",
      "originalQuantity": 9,
      "originalUnit": "kg",
      "normalizedQuantity": 9000,
      "normalizedUnit": "gr.",
      "comment": "",
      "allergens": [],
      "type": "legumes"
    }],
  "preparation": "Trancher les betteraves, ciseler la ciboulette. Tout mélanger.\n\nSaler, poivrer et goûter.",
  "prepAlt": null,
  "permissionWrite": [],
  "publishDate": "2024-06-17T18:02:00Z"
}
