
{
  "uuid": "cxpu5hholt9i",
  "slug": "lemon-curd-vegan-versi_cxpu5hholt9i",
  "title": "Lemon Curd Vegan - Version Tarte Au Citron Sans Gluten",
  "draft": false,
  "typeR": "dessert",
  "categories": ["Sucrée"],
  "regime": ["vegan","sans-gluten"],
  "cuisson": true,
  "serveHot": false,
  "plate": 10,
  "quantite_desc": "un ramequin + un biscuit par personnes",
  "check": false,
  "checkAlwaysOk": false,
  "materiel": null,
  "ingredients": [{
      "uuid": "htp5ma",
      "name": "Curcuma moulu",
      "originalQuantity": 6,
      "originalUnit": "gr.",
      "normalizedQuantity": 6,
      "normalizedUnit": "gr.",
      "comment": "",
      "allergens": [],
      "type": "epices"
    },{
      "uuid": "8j3hna",
      "name": "Margarine végétale spécial cuisson",
      "originalQuantity": 200,
      "originalUnit": "gr.",
      "normalizedQuantity": 200,
      "normalizedUnit": "gr.",
      "comment": "",
      "allergens": [],
      "type": "frais"
    },{
      "uuid": "8nbcjp",
      "name": "Fécule de maïs (Maïzena)",
      "originalQuantity": 75,
      "originalUnit": "gr.",
      "normalizedQuantity": 75,
      "normalizedUnit": "gr.",
      "comment": "",
      "allergens": [],
      "type": "lof"
    },{
      "uuid": "gpeob7",
      "name": "Lait de soja",
      "originalQuantity": 300,
      "originalUnit": "ml",
      "normalizedQuantity": 300,
      "normalizedUnit": "ml",
      "comment": "",
      "allergens": ["Soja"],
      "type": "lof"
    },{
      "uuid": "u9z2he",
      "name": "Sucre en poudre",
      "originalQuantity": 300,
      "originalUnit": "gr.",
      "normalizedQuantity": 300,
      "normalizedUnit": "gr.",
      "comment": "",
      "allergens": [],
      "type": "sucres"
    },{
      "uuid": "e4mjd1",
      "name": "Jus de citron",
      "originalQuantity": 500,
      "originalUnit": "ml",
      "normalizedQuantity": 500,
      "normalizedUnit": "ml",
      "comment": "",
      "allergens": [],
      "type": "sucres"
    }],
  "preparation": "Dans une casserole, mélanger la fécule de maïs et le sucre. Délayer au fouet en ajoutant le lait petit à petit. Ajouter le jus de citron.\n\nFaire cuire sur feu moyen en mélangeant continuellement au fouet jusqu’à ce que la crème bouillonne et épaississe légèrement (patience, ça peut prendre un peu de temps). Laisser bouillir environ 1min sans cesser de remuer. Retirer du feu, ajoutez immédiatement la margarine puis fouetter longuement jusqu’à ce que la crème soit bien lisse et homogène.\n\nVerser dans les ramequins, laisser refroidir puis placer au frais. Servir avec deux biscuits végan sans gluten.",
  "prepAlt": [{"recetteAlt":"tarte-au-citron-vegane_5fh2krusjaqlzhhcjtbqo"}],
  "permissionWrite": [],
  "publishDate": "2024-06-17T20:30:00Z"
}
