
{
  "uuid": "cbz36e69mmfo",
  "slug": "soupe-de-carotte-orang_cbz36e69mmfo",
  "title": "Soupe De Carotte Orange Épicée",
  "draft": false,
  "typeR": "entree",
  "categories": ["Soupe"],
  "regime": ["vegan","sans-gluten"],
  "cuisson": true,
  "serveHot": true,
  "plate": 100,
  "quantite_desc": null,
  "check": true,
  "checkAlwaysOk": false,
  "materiel": null,
  "ingredients": [{
      "uuid": "rtavky",
      "name": "Oignon",
      "originalQuantity": 5,
      "originalUnit": "kg",
      "normalizedQuantity": 5000,
      "normalizedUnit": "gr.",
      "comment": "",
      "allergens": [],
      "type": "legumes"
    },{
      "uuid": "eouu0v",
      "name": "Carotte",
      "originalQuantity": 12,
      "originalUnit": "kg",
      "normalizedQuantity": 12000,
      "normalizedUnit": "gr.",
      "comment": "",
      "allergens": [],
      "type": "legumes"
    },{
      "uuid": "chfwwq",
      "name": "Crème soja",
      "originalQuantity": 1.5,
      "originalUnit": "l.",
      "normalizedQuantity": 1500,
      "normalizedUnit": "ml",
      "comment": "",
      "allergens": ["Soja"],
      "type": "lof"
    },{
      "uuid": "atccqu",
      "name": "Huile végétale",
      "originalQuantity": 250,
      "originalUnit": "ml",
      "normalizedQuantity": 250,
      "normalizedUnit": "ml",
      "comment": "",
      "allergens": [],
      "type": "lof"
    },{
      "uuid": "dex52s",
      "name": "mélange 4 épices",
      "originalQuantity": 75,
      "originalUnit": "gr.",
      "normalizedQuantity": 75,
      "normalizedUnit": "gr.",
      "comment": "",
      "allergens": [],
      "type": "epices"
    },{
      "uuid": "7jceco",
      "name": "Curry",
      "originalQuantity": 75,
      "originalUnit": "gr.",
      "normalizedQuantity": 75,
      "normalizedUnit": "gr.",
      "comment": "",
      "allergens": [],
      "type": "epices"
    },{
      "uuid": "gzi2ry",
      "name": "Jus d'orange",
      "originalQuantity": 4,
      "originalUnit": "l.",
      "normalizedQuantity": 4000,
      "normalizedUnit": "ml",
      "comment": "",
      "allergens": [],
      "type": "sucres"
    }],
  "preparation": "laver et brosser les carottes puis les râper .\n\ncouper les oignons pas forcément très finement\n\nfaire revenir les oignons et les épices dans l'huile quand il sont légèrement dorés ajouter les carottes\n\najouter l'eau et laisser cuire 30 mn\n\nmélanger le jus d'orange et la crème de soja les inclure dans la soupe et mixer le tout\n\nà faire refroidir au moins une heure si servie froide",
  "prepAlt": null,
  "permissionWrite": [],
  "publishDate": "2025-06-15T12:40:00Z"
}
